{
  "db_name": "PostgreSQL",
  "query": "SELECT song_id, artist, title, yturl, isingurl FROM songs ORDER BY (artist, title)",
  "describe": {
    "columns": [
      {
        "ordinal": 0,
        "name": "song_id",
        "type_info": "Int4"
      },
      {
        "ordinal": 1,
        "name": "artist",
        "type_info": "Text"
      },
      {
        "ordinal": 2,
        "name": "title",
        "type_info": "Text"
      },
      {
        "ordinal": 3,
        "name": "yturl",
        "type_info": "Text"
      },
      {
        "ordinal": 4,
        "name": "isingurl",
        "type_info": "Text"
      }
    ],
    "parameters": {
      "Left": []
    },
    "nullable": [
      false,
      false,
      false,
      true,
      true
    ]
  },
  "hash": "096b6fcc96cab34575456fe36a0320f60f314dc92d0e008537ad6bd3735140c7"
}
